iceduck/__init__.py
iceduck/iceberg.py
iceduck-0.1.0.dist-info/METADATA
iceduck-0.1.0.dist-info/WHEEL
iceduck-0.1.0.dist-info/top_level.txt
iceduck-0.1.0.dist-info/RECORD
