Metadata-Version: 2.4
Name: iceduck
Version: 0.1.0
Summary: DuckDB wrapper with iceberg writer
Requires-Python: >=3.12
Requires-Dist: duckdb>=1.2.2
Requires-Dist: numpy>=2.2.4
Requires-Dist: polars>=1.29.0
Requires-Dist: pyiceberg[duckdb,glue,pandas,sql-sqlite]>=0.9.0
